Books_pkg/__init__.py
Books_pkg/books.csv
Books_pkg/buscar_books.py
Books_pkg/random_books.py
Books_pkg-1.0.3.dist-info/METADATA
Books_pkg-1.0.3.dist-info/WHEEL
Books_pkg-1.0.3.dist-info/top_level.txt
Books_pkg-1.0.3.dist-info/RECORD
