Metadata-Version: 2.1
Name: Books_pkg
Version: 1.0.3
Summary: Es una libreria en la cual podremos encontrar el autor y el libro, de pende el que se escriba
Author: Milton Alejandro Angel Cardenas 
Author-email: milton_ac@tesch.edu.mx
Requires-Dist: pandas
Requires-Dist: twine
Requires-Dist: wheel
Requires-Dist: setuptools
